Workbook

Sheet Flujo
B2: Centro Escolar LOMAS YOUNG ENGINEERS
B3: Flujo de efectivo vs. presupuesto
B4: Ciclo escolar 2025-2026
B5: BANCOS | C5: BANORTE | D5: BBVA | E5: DOLARAPP | F5: MP | N5: TOTAL | O5: 45870
B6: Saldo inicial caja y bancos | C6: 10177.69 | D6: 4663.9 | E6: =41.77*18.5 -> 772.745 | F6: 172.08 | N6: =SUM(C6:M6) -> 15786.415
B7: Concepto/mes | C7: 45870 | D7: 45901 | E7: 45931 | F7: 45962 | G7: 45992 | H7: 46023 | I7: 46054 | J7: 46082 | K7: 46113 | L7: 46143 | M7: 46174 | N7: 46204 | O7: Total
B8: INGRESOS
B9: Aportaciones de Socios | C9: 20847.51 | D9: 0 | E9: =2215.99+1624.58 -> 3840.57 | F9: 0 | G9: =12736.64+7434.62+40911.6 -> 61082.86 | H9: 0 | I9: 0 | J9: 0 | K9: 0 | L9: 0 | M9: 0 | N9: 0 | O9: =SUM(C9:N9) -> 85770.94
B10: ALIANZA CDI | C10: 38413.07 | D10: 23200 | E10: 37819.99 | F10: 32713.16 | G10: 0 | H10: 17998.56 | I10: 0 | J10: 0 | K10: 0 | L10: 0 | M10: 0 | N10: 0 | O10: =SUM(C10:N10) -> 150144.78
B11: ALIANZA ALEGRO MONTESSORI | C11: 0 | D11: 0 | E11: 1481 | F11: =417.6 -> 417.6 | G11: 1670.4 | H11: 835.2 | I11: 0 | J11: 0 | K11: 0 | L11: 0 | M11: 0 | N11: 0 | O11: =SUM(C11:N11) -> 4404.2
B12: Total ingresos | C12: =SUM(C9:C11) -> 59260.58 | D12: =SUM(D9:D11) -> 23200 | E12: =SUM(E9:E11) -> 43141.56 | F12: =SUM(F9:F11) -> 33130.76 | G12: =SUM(G9:G11) -> 62753.26 | H12: =SUM(H9:H11) -> 18833.76 | I12: =SUM(I9:I11) -> 0 | J12: =SUM(J9:J11) -> 0 | ... O12: =SUM(O9:O11) -> 240319.92
B13: GASTOS
B14: Nomina | C14: =Nomina!B9*-1 -> -3625 | D14: =Nomina!C9*-1 -> -15250.13 | E14: =Nomina!D9*-1 -> -13832.46 | F14: =Nomina!E9*-1 -> -13129.69 | G14: =Nomina!F9*-1 -> -12830.9 | H14: =Nomina!G9*-1 -> -10581.38 | I14: =Nomina!H9*-1 -> 0 | J14: =Nomina!I9*-1 -> 0 | ... N14: =Nomina!M9*-1 -> 0 | O14: =SUM(C14:N14) -> -69249.56
B15: Aguinaldo | C15: 0 | D15: 0 | E15: 0 | F15: 0 | G15: =-4423.2-1650 -> -6073.2 | H15: 0 | I15: 0 | J15: 0 | K15: 0 | L15: 0 | M15: 0 | N15: 0 | O15: =SUM(C15:N15) -> -6073.2
C16: 0 | D16: 0 | E16: 0 | F16: 0 | G16: 0 | H16: 0 | I16: 0 | J16: 0 | K16: 0 | L16: 0 | M16: 0 | N16: 0 | O16: =SUM(C16:N16) -> 0
B17: Impuestos federales | C17: =-702-50 -> -752 | D17: 0 | E17: -1287 | F17: -1118 | G17: -1195 | H17: -1043 | I17: 0 | J17: 0 | K17: 0 | L17: 0 | M17: 0 | N17: 0 | O17: =SUM(C17:N17) -> -5395
B18: SEO SIMPLE | C18: 0 | D18: 0 | E18: -8120 | F18: -8120 | G18: -6960 | H18: -6960 | I18: 0 | J18: 0 | K18: 0 | L18: 0 | M18: 0 | N18: 0 | O18: =SUM(C18:N18) -> -30160
B19: Gob DF | C19: -182 | D19: 0 | E19: -505 | F19: -617 | G19: -437 | H19: -544 | I19: 0 | J19: 0 | K19: 0 | L19: 0 | M19: 0 | N19: 0 | O19: =SUM(C19:N19) -> -2285
B20: IMSS | C20: -2831.63 | D20: 0 | E20: -2701.2 | F20: -8587.25 | G20: -2701 | H20: 0 | I20: 0 | J20: 0 | K20: 0 | L20: 0 | M20: 0 | N20: 0 | O20: =SUM(C20:N20) -> -16821.08
B21: Mantenimiento | C21: -2262 | D21: 0 | E21: 0 | F21: 0 | G21: 0 | H21: 0 | I21: 0 | J21: 0 | K21: 0 | L21: 0 | M21: 0 | N21: 0 | O21: =SUM(C21:N21) -> -2262
B22: Comisiones | C22: =-5-5-0.8-0.8-400-64 -> -475.6 | D22: 0 | E22: =-5.8+-5.8+-5.8+-5.8+-5.8+-5.8 -> -34.8 | F22: =-5-0.8-5-0.8-5-0.8-5-0.8 -> -23.2 | G22: =-5-0.8-5-0.8-5-0.8-5-0.8-5-0.8-5-0.8-5-0.8 -> -40.6 | H22: =-5-0.8-5-0.8-5-0.8-5-0.8-5-0.8 -> -29 | I22: 0 | J22: 0 | K22: 0 | L22: 0 | M22: 0 | N22: 0 | O22: =SUM(C22:N22) -> -603.2
B23: Comisiones P.Moral Banortey BBVA | C23: 0 | D23: 0 | E23: =-400-64 -> -464 | F23: =-464-328.57 -> -792.57 | G23: -464 | H23: -464 | I23: 0 | J23: 0 | K23: 0 | L23: 0 | M23: 0 | N23: 0 | O23: =SUM(C23:N23) -> -2184.57
B24: Contadores BHC | C24: -8932 | D24: 0 | E24: -20184 | F24: -8932 | G24: =-17864 -> -17864 | H24: -11252 | I24: 0 | J24: 0 | K24: 0 | L24: 0 | M24: 0 | N24: 0 | O24: =SUM(C24:N24) -> -67164
B25: Gastos en Gral | C25: =-12407.72-290-926.59 -> -13624.31 | D25: =-926.59 -> -926.59 | E25: =-926.59-1480.78-5798.3 -> -8205.67 | F25: =-926.59 -> -926.59 | G25: 0 | H25: -660 | I25: 0 | J25: 0 | K25: 0 | L25: 0 | M25: 0 | N25: 0 | O25: =SUM(C25:N25) -> -24343.16
B26: Fee Young Engineers | C26: -5791.14 | D26: -5744.83 | E26: -5648.76 | F26: 0 | G26: -12941.06 | H26: -12941.06 | I26: 0 | J26: 0 | K26: 0 | L26: 0 | M26: 0 | N26: 0 | O26: =SUM(C26:N26) -> -43066.85 | P26: Amex
B27: Suscripciones | C27: =Suscripción!B10*-1 -> -146 | D27: =Suscripción!C10*-1 -> -2356.79 | E27: =Suscripción!D10*-1 -> -702.8 | F27: =Suscripción!E10*-1 -> -702.8 | G27: =Suscripción!F10*-1 -> -702.8 | H27: =Suscripción!G10*-1 -> -702.8 | I27: =Suscripción!H10*-1 -> 0 | J27: =Suscripción!I10*-1 -> 0 | ... N27: =Suscripción!M10*-1 -> 0 | O27: =SUM(C27:N27) -> -5313.99
B28: Meses Sin Intereses | C28: ='Meses Sin Inter'!D5*-1 -> -1684.76 | D28: ='Meses Sin Inter'!E5*-1 -> -1684.76 | E28: ='Meses Sin Inter'!F5*-1 -> -1684.76 | F28: -1684.76 | G28: ='Meses Sin Inter'!H5*-1 -> -3671.58 | H28: ='Meses Sin Inter'!I5*-1 -> -3671.58 | I28: ='Meses Sin Inter'!J5*-1 -> -3671.58 | J28: ='Meses Sin Inter'!K5*-1 -> -3671.58 | K28: ='Meses Sin Inter'!L5*-1 -> -3671.58 | L28: ='Meses Sin Inter'!M5*-1 -> -1684.76 | M28: ='Meses Sin Inter'!N5*-1 -> -758.17 | N28: ='Meses Sin Inter'!O5*-1 -> -758.17 | O28: =SUM(C28:N28) -> -28298.04
B29: Renta | C29: -1044 | D29: -1044 | E29: -1044 | F29: -1044 | G29: -1044 | H29: -1044 | I29: 0 | J29: 0 | K29: 0 | L29: 0 | M29: 0 | N29: 0 | O29: =SUM(C29:N29) -> -6264
B30: Papelería y mobiliario | C30: =-3300-630-430.73-278 -> -4638.73 | D30: =-476-420-1026 -> -1922 | E30: -420 | F30: 0 | G30: 0 | H30: 0 | I30: 0 | J30: 0 | K30: 0 | L30: 0 | M30: 0 | N30: 0 | O30: =SUM(C30:N30) -> -6980.73
B31: Meses Diferidos | C31: 0 | D31: 0 | E31: 0 | F31: 0 | G31: 0 | H31: 0 | I31: 0 | J31: 0 | K31: 0 | L31: 0 | M31: 0 | N31: 0 | O31: =SUM(C31:N31) -> 0
C32: 0 | D32: 0 | E32: 0 | F32: 0 | G32: 0 | H32: 0 | I32: 0 | J32: 0 | K32: 0 | L32: 0 | M32: 0 | N32: 0 | O32: 0
B33: Total gastos | C33: =SUM(C14:C32) -> -45989.17 | D33: =SUM(D14:D32) -> -28929.1 | E33: =SUM(E14:E32) -> -64834.45 | F33: =SUM(F14:F32) -> -45677.86 | G33: =SUM(G14:G32) -> -66925.14 | H33: =SUM(H14:H32) -> -49892.82 | I33: =SUM(I14:I32) -> -3671.58 | J33: =SUM(J14:J32) -> -3671.58 | ... O33: =SUM(O14:O32) -> -316464.38
B34: Total Ingresos | C34: =C12 -> 59260.58 | D34: =D12 -> 23200 | E34: =E12 -> 43141.56 | F34: =F12 -> 33130.76 | G34: =G12 -> 62753.26 | H34: =H12 -> 18833.76 | I34: =I12 -> 0 | J34: =J12 -> 0 | ... O34: =O12 -> 240319.92
B35: Total Gastos | C35: =C33 -> -45989.17 | D35: =D33 -> -28929.1 | E35: =E33 -> -64834.45 | F35: =F33 -> -45677.86 | G35: =G33 -> -66925.14 | H35: =H33 -> -49892.82 | I35: =I33 -> -3671.58 | J35: =J33 -> -3671.58 | ... O35: =O33 -> -316464.38
B36: Diferencia | C36: =C34+C35 -> 13271.41 | D36: =D34+D35 -> -5729.1 | E36: =E34+E35 -> -21692.89 | F36: =F34+F35 -> -12547.1 | G36: =G34+G35 -> -4171.88 | H36: =H34+H35 -> -31059.06 | I36: =I34+I35 -> -3671.58 | J36: =J34+J35 -> -3671.58 | ... O36: =O34+O35 -> -76144.46
B39: Saldo Inicial en caja y bancos | C39: 5996 | D39: 14198 | E39: 0 | F39: 0 | G39: 0 | H39: 0 | I39: 0 | J39: 0 | K39: 0 | L39: 0 | M39: 0 | N39: 0 | O39: =SUM(C39:N39) -> 20194
B40: Saldo Final en caja y bancos | C40: 14198 | D40: 15786.42 | E40: 0 | F40: 0 | G40: 0 | H40: 0 | I40: 0 | J40: 0 | K40: 0 | L40: 0 | M40: 0 | N40: 0 | O40: =SUM(C40:N40) -> 29984.42

Sheet Meses Sin Inter
A1: NO TOCAR
A5: BANCO | B5: =B20+B33+B50+B67+B84 -> -26752.82 | C5: =C20+C33+C50+C67+C84 -> 3369.52 | D5: =D20+D33+D50+D67+D84 -> 1684.76 | E5: =E20+E33+E50+E67+E84 -> 1684.76 | F5: =F20+F33+F50+F67+F84 -> 1684.76 | G5: =G20+G33+G50+G67+G84 -> 3671.58 | H5: =H20+H33+H50+H67+H84 -> 3671.58 | I5: =I20+I33+I50+I67+I84 -> 3671.58 | ... W5: =W20+W33+W50+W67+W84 -> 0
A6: Amex | B6: Monto Original | C6: 45839 | D6: 45870 | E6: 45901 | F6: 45931 | G6: 45962 | H6: 45992 | I6: 46023 | J6: 46054 | K6: 46082 | L6: 46113 | M6: 46143 | N6: 46174 | O6: 46204 | P6: 46235 | Q6: 46266 | R6: 46296 | S6: 46327 | T6: 46357 | U6: 46388 | V6: 46419 | W6: 46447
A7: Curso MKT | B7: -11119 | C7: 1853.18 | D7: 926.59 | E7: 926.59 | F7: 926.59 | G7: 926.59 | H7: 926.59 | I7: 926.59 | J7: 926.59 | K7: 926.59 | L7: 926.59 | M7: 926.59
A8: MacStore | B8: -13647 | C8: 1516.34 | D8: 758.17 | E8: 758.17 | F8: 758.17 | G8: 758.17 | H8: 758.17 | I8: 758.17 | J8: 758.17 | K8: 758.17 | L8: 758.17 | M8: 758.17 | N8: 758.17 | O8: 758.17 | P8: 758.17 | Q8: 758.17 | R8: 758.17 | S8: 758.17
A9: Pagos Dif Amex | B9: =-1643.63-295.85-47.34 -> -1986.82 | G9: 1986.82 | H9: 1986.82 | I9: 1986.82 | J9: 1986.82 | K9: 1986.82 | L9: 1986.82
B20: =SUM(B7:B19) -> -26752.82 | C20: =SUM(C7:C19) -> 3369.52 | D20: =SUM(D7:D19) -> 1684.76 | E20: =SUM(E7:E19) -> 1684.76 | F20: =SUM(F7:F19) -> 1684.76 | G20: =SUM(G7:G19) -> 3671.58 | H20: =SUM(H7:H19) -> 3671.58 | I20: =SUM(I7:I19) -> 3671.58 | ... W20: =SUM(W7:W19) -> 0
C22: 45870 | D22: 45870 | E22: 45901 | F22: 45931 | G22: 45962 | H22: 45992 | I22: 46023 | J22: 46054 | K22: 46082 | L22: 46113 | M22: 46143 | N22: 46174 | O22: 46204 | P22: 46235 | Q22: 46266 | R22: 46296 | S22: 46327 | T22: 46357 | U22: 46388 | V22: 46419 | W22: 46447
B33: =SUM(B23:B32) -> 0 | C33: =SUM(C23:C32) -> 0 | D33: =SUM(D23:D32) -> 0 | E33: =SUM(E23:E32) -> 0 | F33: =SUM(F23:F32) -> 0 | G33: =SUM(G23:G32) -> 0 | H33: =SUM(H23:H32) -> 0 | I33: =SUM(I23:I32) -> 0 | ... W33: =SUM(W23:W32) -> 0
C35: 45870 | D35: 45870 | E35: 45901 | F35: 45931 | G35: 45962 | H35: 45992 | I35: 46023 | J35: 46054 | K35: 46082 | L35: 46113 | M35: 46143 | N35: 46174 | O35: 46204 | P35: 46235 | Q35: 46266 | R35: 46296 | S35: 46327 | T35: 46357 | U35: 46388 | V35: 46419 | W35: 46447
B50: =SUM(B36:B49) -> 0 | C50: =SUM(C36:C49) -> 0 | D50: =SUM(D36:D49) -> 0 | E50: =SUM(E36:E49) -> 0 | F50: =SUM(F36:F49) -> 0 | G50: =SUM(G36:G49) -> 0 | H50: =SUM(H36:H49) -> 0 | I50: =SUM(I36:I49) -> 0 | ... W50: =SUM(W36:W49) -> 0
C52: 45870 | D52: 45870 | E52: 45901 | F52: 45931 | G52: 45962 | H52: 45992 | I52: 46023 | J52: 46054 | K52: 46082 | L52: 46113 | M52: 46143 | N52: 46174 | O52: 46204 | P52: 46235 | Q52: 46266 | R52: 46296 | S52: 46327 | T52: 46357 | U52: 46388 | V52: 46419 | W52: 46447
B67: =SUM(B53:B66) -> 0 | C67: =SUM(C53:C66) -> 0 | D67: =SUM(D53:D66) -> 0 | E67: =SUM(E53:E66) -> 0 | F67: =SUM(F53:F66) -> 0 | G67: =SUM(G53:G66) -> 0 | H67: =SUM(H53:H66) -> 0 | I67: =SUM(I53:I66) -> 0 | ... W67: =SUM(W53:W66) -> 0
B69: Monto Original | C69: 45870 | D69: 45870 | E69: 45901 | F69: 45931 | G69: 45962 | H69: 45992 | I69: 46023 | J69: 46054 | K69: 46082 | L69: 46113 | M69: 46143 | N69: 46174 | O69: 46204 | P69: 46235 | Q69: 46266 | R69: 46296 | S69: 46327 | T69: 46357 | U69: 46388 | V69: 46419 | W69: 46447
B84: =SUM(B70:B83) -> 0 | C84: =SUM(C70:C83) -> 0 | D84: =SUM(D70:D83) -> 0 | E84: =SUM(E70:E83) -> 0 | F84: =SUM(F70:F83) -> 0 | G84: =SUM(G70:G83) -> 0 | H84: =SUM(H70:H83) -> 0 | I84: =SUM(I70:I83) -> 0 | ... W84: =SUM(W70:W83) -> 0

Sheet Suscripción
A1: Suscripción
A2: Concepto/mes | B2: 45870 | C2: 45901 | D2: 45931 | E2: 45962 | F2: 45992 | G2: 46023 | H2: 46054 | I2: 46082 | J2: 46113 | K2: 46143 | L2: 46174 | M2: 46204 | N2: Total
A3: Apple | B3: 17 | C3: 17 | D3: 17 | E3: 17 | F3: 17 | G3: 17 | N3: =SUM(B3:M3) -> 102
A4: Apple Music | B4: 129 | C4: 129 | D4: 129 | E4: 129 | F4: 129 | G4: 129 | N4: =SUM(B4:M4) -> 774
A5: Google Suite | C5: =720+1113.6+377.19 -> 2210.79 | D5: 556.8 | E5: 556.8 | F5: 556.8 | G5: 556.8
N6: =SUM(B6:M6) -> 0
N7: =SUM(B7:M7) -> 0
N9: =SUM(B9:M9) -> 0
A10: Tota | B10: =SUM(B3:B9) -> 146 | C10: =SUM(C3:C9) -> 2356.79 | D10: =SUM(D3:D9) -> 702.8 | E10: =SUM(E3:E9) -> 702.8 | F10: =SUM(F3:F9) -> 702.8 | G10: =SUM(G3:G9) -> 702.8 | H10: =SUM(H3:H9) -> 0 | I10: =SUM(I3:I9) -> 0 | ... M10: =SUM(M3:M9) -> 0 | N10: =SUM(B10:M10) -> 5313.99

Sheet Nomina
A1: NOMINA
A2: Concepto/mes | B2: 45870 | C2: 45901 | D2: 45931 | E2: 45962 | F2: 45992 | G2: 46023 | H2: 46054 | I2: 46082 | J2: 46113 | K2: 46143 | L2: 46174 | M2: 46204 | N2: Total
A3: CHANTAL | B3: 0 | C3: 5000 | D3: 4999.78 | E3: 4999.78 | F3: 3999.83 | G3: 5290.69 | H3: 0 | I3: 0 | J3: 0 | K3: 0 | L3: 0 | M3: 0 | N3: =SUM(B5:M5) -> 52200.21
B4: 2500 | C4: 6120.05 | D4: 4999.78 | E4: 3999.83 | F4: 4999.78 | G4: 5290.69 | H4: 0 | I4: 0 | J4: 0 | K4: 0 | L4: 0 | M4: 0
B5: =SUM(B3:B4) -> 2500 | C5: =SUM(C3:C4) -> 11120.05 | D5: =SUM(D3:D4) -> 9999.56 | E5: =SUM(E3:E4) -> 8999.61 | F5: =SUM(F3:F4) -> 8999.61 | G5: =SUM(G3:G4) -> 10581.38 | H5: =SUM(H3:H4) -> 0 | I5: =SUM(I3:I4) -> 0 | ... M5: =SUM(M3:M4) -> 0
A6: JENNY | B6: 0 | C6: 2065.04 | D6: 1767.86 | E6: 2065.04 | F6: 2065.04 | G6: 0 | H6: 0 | I6: 0 | J6: 0 | K6: 0 | L6: 0 | M6: 0 | N6: =SUM(B8:M8) -> 17049.35
B7: 1125 | C7: 2065.04 | D7: 2065.04 | E7: 2065.04 | F7: 1766.25 | G7: 0 | H7: 0 | I7: 0 | J7: 0 | K7: 0 | L7: 0 | M7: 0
B8: =SUM(B6:B7) -> 1125 | C8: =SUM(C6:C7) -> 4130.08 | D8: =SUM(D6:D7) -> 3832.9 | E8: =SUM(E6:E7) -> 4130.08 | F8: =SUM(F6:F7) -> 3831.29 | G8: =SUM(G6:G7) -> 0 | H8: =SUM(H6:H7) -> 0 | I8: =SUM(I6:I7) -> 0 | ... M8: =SUM(M6:M7) -> 0
A9: GRAN TOTAL | B9: =B5+B8 -> 3625 | C9: =C5+C8 -> 15250.13 | D9: =D5+D8 -> 13832.46 | E9: =E5+E8 -> 13129.69 | F9: =F5+F8 -> 12830.9 | G9: =G5+G8 -> 10581.38 | H9: =H5+H8 -> 0 | I9: =I5+I8 -> 0 | ... M9: =M5+M8 -> 0 | N9: =SUM(B9:M9) -> 69249.56
